[
  {
    "id": "455135669",
    "beginAt": "2019-07-19T21:36:17Z",
    "endAt": "2019-07-19T23:26:57Z"
  },
  {
    "id": "456834627",
    "beginAt": "2019-07-23T14:04:59Z",
    "endAt": "2019-07-23T15:37:27Z"
  },
  {
    "id": "457342195",
    "beginAt": "2019-07-24T16:11:45Z",
    "endAt": "2019-07-24T17:30:03Z"
  },
  {
    "id": "457802109",
    "beginAt": "2019-07-25T16:03:02Z",
    "endAt": "2019-07-25T16:03:02Z"
  },
  {
    "id": "460602343",
    "beginAt": "2019-07-31T17:38:38Z",
    "endAt": "2019-07-31T19:41:56Z"
  }
]