[
  {
    "id": "464835689",
    "beginAt": "2019-08-09T18:01:16Z",
    "endAt": "2019-08-10T02:02:12Z"
  },
  {
    "id": "465329539",
    "beginAt": "2019-08-10T18:15:15Z",
    "endAt": "2019-08-11T01:56:34Z"
  },
  {
    "id": "466237814",
    "beginAt": "2019-08-12T17:58:02Z",
    "endAt": "2019-08-12T23:19:11Z"
  },
  {
    "id": "466672858",
    "beginAt": "2019-08-13T17:01:37Z",
    "endAt": "2019-08-13T22:58:33Z"
  },
  {
    "id": "467170707",
    "beginAt": "2019-08-14T18:00:12Z",
    "endAt": "2019-08-14T21:27:19Z"
  },
  {
    "id": "468080693",
    "beginAt": "2019-08-16T18:00:50Z",
    "endAt": "2019-08-17T00:54:56Z"
  },
  {
    "id": "468524445",
    "beginAt": "2019-08-17T17:00:39Z",
    "endAt": "2019-08-18T00:02:56Z"
  },
  {
    "id": "469221489",
    "beginAt": "2019-08-19T02:23:58Z",
    "endAt": "2019-08-19T07:04:37Z"
  },
  {
    "id": "469223322",
    "beginAt": "2019-08-19T02:29:43Z",
    "endAt": "2019-08-19T05:05:27Z"
  },
  {
    "id": "469433177",
    "beginAt": "2019-08-19T17:02:24Z",
    "endAt": "2019-08-20T01:15:28Z"
  },
  {
    "id": "469909405",
    "beginAt": "2019-08-20T18:02:31Z",
    "endAt": "2019-08-20T18:02:31Z"
  }
]