[
  {
    "id": "462901042",
    "beginAt": "2019-08-05T15:26:38Z",
    "endAt": "2019-08-05T21:57:02Z"
  },
  {
    "id": "463915398",
    "beginAt": "2019-08-07T18:39:17Z",
    "endAt": "2019-08-07T20:40:39Z"
  },
  {
    "id": "464373324",
    "beginAt": "2019-08-08T18:11:26Z",
    "endAt": "2019-08-08T21:17:14Z"
  },
  {
    "id": "465215231",
    "beginAt": "2019-08-10T13:31:25Z",
    "endAt": "2019-08-10T16:22:00Z"
  },
  {
    "id": "465771980",
    "beginAt": "2019-08-11T17:07:53Z",
    "endAt": "2019-08-11T20:37:04Z"
  },
  {
    "id": "468918132",
    "beginAt": "2019-08-18T13:32:17Z",
    "endAt": "2019-08-18T13:32:17Z"
  }
]